Metadata-Version: 1.1
Name: ChemSpiPy
Version: 2.0.0
Summary: A simple Python wrapper around the ChemSpider Web Services.
Home-page: https://github.com/mcs07/ChemSpiPy
Author: Matt Swain
Author-email: m.swain@me.com
License: MIT
Keywords: chemistry cheminformatics chemspider rsc rest api
Platform: UNKNOWN
Classifier: Environment :: Console
Classifier: Intended Audience :: Developers
Classifier: Intended Audience :: Healthcare Industry
Classifier: Intended Audience :: Science/Research
Classifier: License :: OSI Approved :: MIT License
Classifier: Operating System :: OS Independent
Classifier: Programming Language :: Python :: 2
Classifier: Programming Language :: Python :: 3
Classifier: Topic :: Scientific/Engineering
Classifier: Topic :: Scientific/Engineering :: Bio-Informatics
Classifier: Topic :: Scientific/Engineering :: Chemistry
Classifier: Topic :: Software Development :: Libraries :: Python Modules
